setup.py
mxsoftpy/BaseDB.py
mxsoftpy/DB.py
mxsoftpy/HTTPMethod.py
mxsoftpy/TableDB.py
mxsoftpy/TreeDB.py
mxsoftpy/__init__.py
mxsoftpy/base.py
mxsoftpy/conf_base.py
mxsoftpy/def_http_code.py
mxsoftpy/exception.py
mxsoftpy/globals.py
mxsoftpy/main.py
mxsoftpy/model.py
mxsoftpy/module.py
mxsoftpy/mqDB.py
mxsoftpy/server.py
mxsoftpy/view.py
mxsoftpy.egg-info/PKG-INFO
mxsoftpy.egg-info/SOURCES.txt
mxsoftpy.egg-info/dependency_links.txt
mxsoftpy.egg-info/requires.txt
mxsoftpy.egg-info/top_level.txt
mxsoftpy/db_def/__init__.py
mxsoftpy/db_def/db_error.py
mxsoftpy/db_def/def_mq.py
mxsoftpy/db_def/def_table.py
mxsoftpy/db_def/def_tree.py
mxsoftpy/db_def/def_type.py