Metadata-Version: 2.1
Name: mxsoftpy
Version: 0.0.20
Summary: 美信python框架
Home-page: https://gitee.com/yuanhao_1998/mxsoftpy.git
Author: great
Author-email: great@mxsoft.com
License: UNKNOWN
Platform: UNKNOWN
